{"_type":"export","__export_format":4,"__export_date":"2023-04-08T00:57:04.627Z","__export_source":"insomnia.desktop.app:v2023.1.0","resources":[{"_id":"req_8e734019d29542da883c23292d3ff760","parentId":"wrk_f8c8ced6f005427f8b580f349fff0f14","modified":1680178829954,"created":1680178795236,"url":"{{ _.url }}/token","name":"getToken","description":"","method":"GET","body":{},"parameters":[],"headers":[],"authentication":{},"metaSortKey":-1680072543832.25,"isPrivate":false,"settingStoreCookies":true,"settingSendCookies":true,"settingDisableRenderRequestBody":false,"settingEncodeUrl":true,"settingRebuildPath":true,"settingFollowRedirects":"global","_type":"request"},{"_id":"wrk_f8c8ced6f005427f8b580f349fff0f14","parentId":null,"modified":1679853943675,"created":1679853943675,"name":"API Laravel","description":"","scope":"collection","_type":"workspace"},{"_id":"req_bda210e196fe48f7a0b3afd56f728701","parentId":"fld_2811262235b244a49eff3c65c6a919c3","modified":1680915149235,"created":1680176452985,"url":"{{ _.url }}/accounts","name":"store","description":"","method":"POST","body":{"mimeType":"application/json","text":"{\n\t\"balance\": 9000,\n\t\"fk_customer\": 1,\n\t\"fk_account_type\": 2\n}\n"},"parameters":[{"id":"pair_c1c5dc9686464b568b010ba797c64dfb","name":"form","value":"{{ _.form_type }}","description":""}],"headers":[{"name":"Content-Type","value":"application/json","id":"pair_2f52098bf96144a08feacf7cb897bf21"},{"id":"pair_5f1c4902332b4e7fb13714347853f327","name":"X-CSRF-TOKEN","value":"{{ _.token }}","description":""}],"authentication":{},"metaSortKey":-1680176736850,"isPrivate":false,"settingStoreCookies":true,"settingSendCookies":true,"settingDisableRenderRequestBody":false,"settingEncodeUrl":true,"settingRebuildPath":true,"settingFollowRedirects":"global","_type":"request"},{"_id":"fld_2811262235b244a49eff3c65c6a919c3","parentId":"wrk_f8c8ced6f005427f8b580f349fff0f14","modified":1680178816859,"created":1680176484629,"name":"Account","description":"","environment":{},"environmentPropertyOrder":null,"metaSortKey":-1680020573433.875,"_type":"request_group"},{"_id":"req_fccb99f3d42044ecb5a0e4d3b2c140ab","parentId":"fld_2811262235b244a49eff3c65c6a919c3","modified":1680915158298,"created":1680176739186,"url":"{{ _.url }}/accounts/{{ _.account_id }}","name":"get","description":"","method":"GET","body":{},"parameters":[{"id":"pair_fe5b1b63073c4297a26073e30be38ea3","name":"form","value":"{{ _.form_type }}","description":""}],"headers":[{"id":"pair_e25f9cacf80842ff8f8f32e512fdc0e2","name":"X-CSRF-TOKEN","value":"{{ _.token }}","description":""}],"authentication":{},"metaSortKey":-1680176735682,"isPrivate":false,"settingStoreCookies":true,"settingSendCookies":true,"settingDisableRenderRequestBody":false,"settingEncodeUrl":true,"settingRebuildPath":true,"settingFollowRedirects":"global","_type":"request"},{"_id":"req_eeb0f8f0ff304a7abd141b8f0c1d4688","parentId":"fld_2811262235b244a49eff3c65c6a919c3","modified":1680915167838,"created":1680176734514,"url":"{{ _.url }}/accounts","name":"getList","description":"","method":"GET","body":{},"parameters":[{"id":"pair_e1da6e1daa3a418fafa3bcf66302b63c","name":"form","value":"{{ _.form_type }}","description":""}],"headers":[{"id":"pair_37462f127fa34f89b14030095dfafcc1","name":"X-CSRF-TOKEN","value":"{{ _.token }}","description":""}],"authentication":{},"metaSortKey":-1680176734514,"isPrivate":false,"settingStoreCookies":true,"settingSendCookies":true,"settingDisableRenderRequestBody":false,"settingEncodeUrl":true,"settingRebuildPath":true,"settingFollowRedirects":"global","_type":"request"},{"_id":"req_3d819b42587541808e2e775cbaa49be9","parentId":"fld_2811262235b244a49eff3c65c6a919c3","modified":1680915174817,"created":1680176722746,"url":"{{ _.url }}/accounts/{{ _.account_id }}","name":"update","description":"","method":"PUT","body":{"mimeType":"application/json","text":"{\n\t\"balance\": 1000,\n\t\"fk_customer\": 2,\n\t\"fk_account_type\": 2\n}"},"parameters":[{"id":"pair_3318b05b480047f38e5f029694ff9f94","name":"form","value":"{{ _.form_type }}","description":""}],"headers":[{"name":"Content-Type","value":"application/json","id":"pair_776d0a73eb9a46018648aa6403a89ae4"},{"id":"pair_1c065c9cdeb5423aaf7f14ace0897ad2","name":"X-CSRF-TOKEN","value":"{{ _.token }}","description":""}],"authentication":{},"metaSortKey":-1680176722746,"isPrivate":false,"settingStoreCookies":true,"settingSendCookies":true,"settingDisableRenderRequestBody":false,"settingEncodeUrl":true,"settingRebuildPath":true,"settingFollowRedirects":"global","_type":"request"},{"_id":"req_1963e6a3692e4a43a2e91d41d49d2286","parentId":"fld_2811262235b244a49eff3c65c6a919c3","modified":1680915181929,"created":1680176709994,"url":"{{ _.url }}/accounts/{{ _.account_id }}","name":"delete","description":"","method":"DELETE","body":{},"parameters":[{"id":"pair_df7c6d439b544d35a73da052893f5d9a","name":"form","value":"{{ _.form_type }}","description":""}],"headers":[{"id":"pair_875c7616f451468fac20f8e16eca3205","name":"X-CSRF-TOKEN","value":"{{ _.token }}","description":""}],"authentication":{},"metaSortKey":-1680176468757,"isPrivate":false,"settingStoreCookies":true,"settingSendCookies":true,"settingDisableRenderRequestBody":false,"settingEncodeUrl":true,"settingRebuildPath":true,"settingFollowRedirects":"global","_type":"request"},{"_id":"req_5a611fdcaf2843c2a0c8f45a3ce5daba","parentId":"fld_1530597c4f7842c1b5302fc5d742cfca","modified":1680915190303,"created":1680177225881,"url":"{{ _.url }}/account_types","name":"store","description":"","method":"POST","body":{"mimeType":"application/json","text":"{\n\t\"type\": \"Teste\"\n}\n"},"parameters":[{"id":"pair_69af2194bd67401d877ac90c869c6ff3","name":"form","value":"{{ _.form_type }}","description":""}],"headers":[{"name":"Content-Type","value":"application/json","id":"pair_2f52098bf96144a08feacf7cb897bf21"},{"id":"pair_5f1c4902332b4e7fb13714347853f327","name":"X-CSRF-TOKEN","value":"{{ _.token }}","description":""}],"authentication":{},"metaSortKey":-1680176736850,"isPrivate":false,"settingStoreCookies":true,"settingSendCookies":true,"settingDisableRenderRequestBody":false,"settingEncodeUrl":true,"settingRebuildPath":true,"settingFollowRedirects":"global","_type":"request"},{"_id":"fld_1530597c4f7842c1b5302fc5d742cfca","parentId":"wrk_f8c8ced6f005427f8b580f349fff0f14","modified":1680179574806,"created":1680177225877,"name":"AccountType","description":"","environment":{},"environmentPropertyOrder":null,"metaSortKey":-1679994588234.6875,"_type":"request_group"},{"_id":"req_0aedc20028e5467fa6fef45be2758e2a","parentId":"fld_1530597c4f7842c1b5302fc5d742cfca","modified":1680915196555,"created":1680177225905,"url":"{{ _.url }}/account_types/{{ _.account_type_id }}","name":"get","description":"","method":"GET","body":{},"parameters":[{"id":"pair_c62fe8fe6f3b4b639734352c340501e0","name":"form","value":"{{ _.form_type }}","description":""}],"headers":[{"id":"pair_e25f9cacf80842ff8f8f32e512fdc0e2","name":"X-CSRF-TOKEN","value":"{{ _.token }}","description":""}],"authentication":{},"metaSortKey":-1680176735682,"isPrivate":false,"settingStoreCookies":true,"settingSendCookies":true,"settingDisableRenderRequestBody":false,"settingEncodeUrl":true,"settingRebuildPath":true,"settingFollowRedirects":"global","_type":"request"},{"_id":"req_eaf2abe48b2f444cbaca85fe8a3d7a19","parentId":"fld_1530597c4f7842c1b5302fc5d742cfca","modified":1680915203473,"created":1680177225899,"url":"{{ _.url }}/account_types","name":"getList","description":"","method":"GET","body":{},"parameters":[{"id":"pair_045e741df88247d9a2e5c68816ca8324","name":"form","value":"{{ _.form_type }}","description":""}],"headers":[{"id":"pair_37462f127fa34f89b14030095dfafcc1","name":"X-CSRF-TOKEN","value":"{{ _.token }}","description":""}],"authentication":{},"metaSortKey":-1680176734514,"isPrivate":false,"settingStoreCookies":true,"settingSendCookies":true,"settingDisableRenderRequestBody":false,"settingEncodeUrl":true,"settingRebuildPath":true,"settingFollowRedirects":"global","_type":"request"},{"_id":"req_6e1b30373a9b45f79f588dff3d342eff","parentId":"fld_1530597c4f7842c1b5302fc5d742cfca","modified":1680915211017,"created":1680177225894,"url":"{{ _.url }}/account_types/{{ _.account_type_id }}","name":"update","description":"","method":"PUT","body":{"mimeType":"application/json","text":"{\n\t\"type\": \"Alterado\"\n}\n"},"parameters":[{"id":"pair_ea7b727bfdef4ac388253f7c8f215e64","name":"form","value":"{{ _.form_type }}","description":""}],"headers":[{"name":"Content-Type","value":"application/json","id":"pair_776d0a73eb9a46018648aa6403a89ae4"},{"id":"pair_1c065c9cdeb5423aaf7f14ace0897ad2","name":"X-CSRF-TOKEN","value":"{{ _.token }}","description":""}],"authentication":{},"metaSortKey":-1680176722746,"isPrivate":false,"settingStoreCookies":true,"settingSendCookies":true,"settingDisableRenderRequestBody":false,"settingEncodeUrl":true,"settingRebuildPath":true,"settingFollowRedirects":"global","_type":"request"},{"_id":"req_da8f7b81358d4ff2bd3758880c79a4ce","parentId":"fld_1530597c4f7842c1b5302fc5d742cfca","modified":1680915216869,"created":1680177225888,"url":"{{ _.url }}/account_types/{{ _.account_type_id }}","name":"delete","description":"","method":"DELETE","body":{},"parameters":[{"id":"pair_3b4baf5c37094d779f7a5b326db2b0f9","name":"form","value":"{{ _.form_type }}","description":""}],"headers":[{"id":"pair_875c7616f451468fac20f8e16eca3205","name":"X-CSRF-TOKEN","value":"{{ _.token }}","description":""}],"authentication":{},"metaSortKey":-1680176468757,"isPrivate":false,"settingStoreCookies":true,"settingSendCookies":true,"settingDisableRenderRequestBody":false,"settingEncodeUrl":true,"settingRebuildPath":true,"settingFollowRedirects":"global","_type":"request"},{"_id":"req_d4b6ed13a72c404197ebdfb3c63b80da","parentId":"fld_0721620471934b308217639f5f1f349c","modified":1680915377134,"created":1680177370621,"url":"{{ _.url }}/addresses","name":"store","description":"","method":"POST","body":{"mimeType":"application/json","text":"{\n\t\"city\": \"Jequié\",\n\t\"state\": \"BA\",\n\t\"cep\": \"45211548\",\n\t\"address\": \"São Judas, 11\"\n}\n"},"parameters":[{"id":"pair_95db27b41ce94c0283c9dfca6d265443","name":"form","value":"{{ _.form_type }}","description":""}],"headers":[{"name":"Content-Type","value":"application/json","id":"pair_2f52098bf96144a08feacf7cb897bf21"},{"id":"pair_5f1c4902332b4e7fb13714347853f327","name":"X-CSRF-TOKEN","value":"{{ _.token }}","description":""}],"authentication":{},"metaSortKey":-1680176736850,"isPrivate":false,"settingStoreCookies":true,"settingSendCookies":true,"settingDisableRenderRequestBody":false,"settingEncodeUrl":true,"settingRebuildPath":true,"settingFollowRedirects":"global","_type":"request"},{"_id":"fld_0721620471934b308217639f5f1f349c","parentId":"wrk_f8c8ced6f005427f8b580f349fff0f14","modified":1680179581240,"created":1680177370618,"name":"Addresses","description":"","environment":{},"environmentPropertyOrder":null,"metaSortKey":-1679981595635.0938,"_type":"request_group"},{"_id":"req_fc8b2b5712df4307b9c33a4e6c927e72","parentId":"fld_0721620471934b308217639f5f1f349c","modified":1680915237320,"created":1680177370643,"url":"{{ _.url }}/addresses/{{ _.address_id }}","name":"get","description":"","method":"GET","body":{},"parameters":[{"id":"pair_aed6c2e464ff4560864c704dc18338b5","name":"form","value":"{{ _.form_type }}","description":""}],"headers":[{"id":"pair_e25f9cacf80842ff8f8f32e512fdc0e2","name":"X-CSRF-TOKEN","value":"{{ _.token }}","description":""}],"authentication":{},"metaSortKey":-1680176735682,"isPrivate":false,"settingStoreCookies":true,"settingSendCookies":true,"settingDisableRenderRequestBody":false,"settingEncodeUrl":true,"settingRebuildPath":true,"settingFollowRedirects":"global","_type":"request"},{"_id":"req_5279266e903a4f7291c46c4d096f803d","parentId":"fld_0721620471934b308217639f5f1f349c","modified":1680915127423,"created":1680177370636,"url":"{{ _.url }}/addresses","name":"getList","description":"","method":"GET","body":{},"parameters":[{"id":"pair_f6421fbbe83b419d96f8d5808700cf31","name":"form","value":"{{ _.form_type }}","description":"","disabled":false}],"headers":[{"id":"pair_37462f127fa34f89b14030095dfafcc1","name":"X-CSRF-TOKEN","value":"{{ _.token }}","description":""}],"authentication":{},"metaSortKey":-1680176734514,"isPrivate":false,"settingStoreCookies":true,"settingSendCookies":true,"settingDisableRenderRequestBody":false,"settingEncodeUrl":true,"settingRebuildPath":true,"settingFollowRedirects":"global","_type":"request"},{"_id":"req_428689c3ac6d4f55bea256c41d158105","parentId":"fld_0721620471934b308217639f5f1f349c","modified":1680915250081,"created":1680177370632,"url":"{{ _.url }}/addresses/{{ _.address_id }}","name":"update","description":"","method":"PUT","body":{"mimeType":"application/json","text":"{\n\t\"city\": \"Jequié\",\n\t\"state\": \"BA\",\n\t\"cep\": \"45211548\",\n\t\"address\": \"São Judas, 11\"\n}\n"},"parameters":[{"id":"pair_a5b9087970f5433c8929869866e96820","name":"form","value":"{{ _.form_type }}","description":""}],"headers":[{"name":"Content-Type","value":"application/json","id":"pair_776d0a73eb9a46018648aa6403a89ae4"},{"id":"pair_1c065c9cdeb5423aaf7f14ace0897ad2","name":"X-CSRF-TOKEN","value":"{{ _.token }}","description":""}],"authentication":{},"metaSortKey":-1680176722746,"isPrivate":false,"settingStoreCookies":true,"settingSendCookies":true,"settingDisableRenderRequestBody":false,"settingEncodeUrl":true,"settingRebuildPath":true,"settingFollowRedirects":"global","_type":"request"},{"_id":"req_b5c7e28a6f8845c9bcea037c22ccd518","parentId":"fld_0721620471934b308217639f5f1f349c","modified":1680915255960,"created":1680177370627,"url":"{{ _.url }}/addresses/{{ _.address_id }}","name":"delete","description":"","method":"DELETE","body":{},"parameters":[{"id":"pair_96831d6c4c124e278a43e21e6d6e83de","name":"form","value":"{{ _.form_type }}","description":""}],"headers":[{"id":"pair_875c7616f451468fac20f8e16eca3205","name":"X-CSRF-TOKEN","value":"{{ _.token }}","description":""}],"authentication":{},"metaSortKey":-1680176468757,"isPrivate":false,"settingStoreCookies":true,"settingSendCookies":true,"settingDisableRenderRequestBody":false,"settingEncodeUrl":true,"settingRebuildPath":true,"settingFollowRedirects":"global","_type":"request"},{"_id":"req_c8188a3e387b4dd79a0fc2cba485b2aa","parentId":"fld_fa32cb243a3c4d97a40fb2712831f889","modified":1680915265059,"created":1680177104037,"url":"{{ _.url }}/customers","name":"store","description":"","method":"POST","body":{"mimeType":"application/json","text":"{\n\t\"phone_number\": \"(11) 988889999\",\n\t\"fk_address\": 2\n}\n"},"parameters":[{"id":"pair_2229043561974c08b36c8c64ed61dff1","name":"form","value":"{{ _.form_type }}","description":""}],"headers":[{"name":"Content-Type","value":"application/json","id":"pair_2f52098bf96144a08feacf7cb897bf21"},{"id":"pair_5f1c4902332b4e7fb13714347853f327","name":"X-CSRF-TOKEN","value":"{{ _.token }}","description":""}],"authentication":{},"metaSortKey":-1680176736850,"isPrivate":false,"settingStoreCookies":true,"settingSendCookies":true,"settingDisableRenderRequestBody":false,"settingEncodeUrl":true,"settingRebuildPath":true,"settingFollowRedirects":"global","_type":"request"},{"_id":"fld_fa32cb243a3c4d97a40fb2712831f889","parentId":"wrk_f8c8ced6f005427f8b580f349fff0f14","modified":1680177104032,"created":1680177104032,"name":"Customer","description":"","environment":{},"environmentPropertyOrder":null,"metaSortKey":-1679968603035.5,"_type":"request_group"},{"_id":"req_e3edbdd1e0264f80aeb4d1be04f75cad","parentId":"fld_fa32cb243a3c4d97a40fb2712831f889","modified":1680915278263,"created":1680177104062,"url":"{{ _.url }}/customers/{{ _.customer_id }}","name":"get","description":"","method":"GET","body":{},"parameters":[{"id":"pair_09d062712eb5498db14ab93d7fd3c459","name":"form","value":"{{ _.form_type }}","description":""}],"headers":[{"id":"pair_e25f9cacf80842ff8f8f32e512fdc0e2","name":"X-CSRF-TOKEN","value":"{{ _.token }}","description":""}],"authentication":{},"metaSortKey":-1680176735682,"isPrivate":false,"settingStoreCookies":true,"settingSendCookies":true,"settingDisableRenderRequestBody":false,"settingEncodeUrl":true,"settingRebuildPath":true,"settingFollowRedirects":"global","_type":"request"},{"_id":"req_d062ab93f0924a048494168ff84fc367","parentId":"fld_fa32cb243a3c4d97a40fb2712831f889","modified":1680915285788,"created":1680177104056,"url":"{{ _.url }}/customers","name":"getList","description":"","method":"GET","body":{},"parameters":[{"id":"pair_7c7df937fa3e43d0bb0afd90118fe710","name":"form","value":"{{ _.form_type }}","description":""}],"headers":[{"id":"pair_37462f127fa34f89b14030095dfafcc1","name":"X-CSRF-TOKEN","value":"{{ _.token }}","description":""}],"authentication":{},"metaSortKey":-1680176734514,"isPrivate":false,"settingStoreCookies":true,"settingSendCookies":true,"settingDisableRenderRequestBody":false,"settingEncodeUrl":true,"settingRebuildPath":true,"settingFollowRedirects":"global","_type":"request"},{"_id":"req_f8b79c8283834121b92656200559b532","parentId":"fld_fa32cb243a3c4d97a40fb2712831f889","modified":1680915291475,"created":1680177104049,"url":"{{ _.url }}/customers/{{ _.customer_id }}","name":"update","description":"","method":"PUT","body":{"mimeType":"application/json","text":"{\n\t\"phone_number\": \"(11) 988889999\",\n\t\"fk_address\": 2\n}\n"},"parameters":[{"id":"pair_5829e9cad4ab407995edc528da538846","name":"form","value":"{{ _.form_type }}","description":""}],"headers":[{"name":"Content-Type","value":"application/json","id":"pair_776d0a73eb9a46018648aa6403a89ae4"},{"id":"pair_1c065c9cdeb5423aaf7f14ace0897ad2","name":"X-CSRF-TOKEN","value":"{{ _.token }}","description":""}],"authentication":{},"metaSortKey":-1680176722746,"isPrivate":false,"settingStoreCookies":true,"settingSendCookies":true,"settingDisableRenderRequestBody":false,"settingEncodeUrl":true,"settingRebuildPath":true,"settingFollowRedirects":"global","_type":"request"},{"_id":"req_b67d601c49f24685b7143bf49e472193","parentId":"fld_fa32cb243a3c4d97a40fb2712831f889","modified":1680915297343,"created":1680177104044,"url":"{{ _.url }}/customers/{{ _.customer_id }}","name":"delete","description":"","method":"DELETE","body":{},"parameters":[{"id":"pair_57b2433f42bc43d78de0b2580c47fd8e","name":"form","value":"{{ _.form_type }}","description":""}],"headers":[{"id":"pair_875c7616f451468fac20f8e16eca3205","name":"X-CSRF-TOKEN","value":"{{ _.token }}","description":""}],"authentication":{},"metaSortKey":-1680176468757,"isPrivate":false,"settingStoreCookies":true,"settingSendCookies":true,"settingDisableRenderRequestBody":false,"settingEncodeUrl":true,"settingRebuildPath":true,"settingFollowRedirects":"global","_type":"request"},{"_id":"req_730ec291ff964762b16ee998d2a51bac","parentId":"fld_bedf24f4d1d14619bd05616fc98f210c","modified":1680915304284,"created":1680177215875,"url":"{{ _.url }}/transactions","name":"store","description":"","method":"POST","body":{"mimeType":"application/json","text":"{\n\t\"date\": \"2023-04-03T19:16:11.000000Z\",\n\t\"amount\": 6000,\n\t\"fk_account\": 2,\n\t\"fk_transaction_type\": 2\n}\n"},"parameters":[{"id":"pair_363bd4de9704485fb33e92fcc1db3b38","name":"form","value":"{{ _.form_type }}","description":""}],"headers":[{"name":"Content-Type","value":"application/json","id":"pair_2f52098bf96144a08feacf7cb897bf21"},{"id":"pair_5f1c4902332b4e7fb13714347853f327","name":"X-CSRF-TOKEN","value":"{{ _.token }}","description":""}],"authentication":{},"metaSortKey":-1680176736850,"isPrivate":false,"settingStoreCookies":true,"settingSendCookies":true,"settingDisableRenderRequestBody":false,"settingEncodeUrl":true,"settingRebuildPath":true,"settingFollowRedirects":"global","_type":"request"},{"_id":"fld_bedf24f4d1d14619bd05616fc98f210c","parentId":"wrk_f8c8ced6f005427f8b580f349fff0f14","modified":1680177215871,"created":1680177215871,"name":"Transaction","description":"","environment":{},"environmentPropertyOrder":null,"metaSortKey":-1679864662238.75,"_type":"request_group"},{"_id":"req_6a4263f5a6c94ef48a9c96bc0492e4f4","parentId":"fld_bedf24f4d1d14619bd05616fc98f210c","modified":1680915309772,"created":1680177215903,"url":"{{ _.url }}/transactions/{{ _.transaction_id }}","name":"get","description":"","method":"GET","body":{},"parameters":[{"id":"pair_c4a051d5cbc346e3a427c38d43634111","name":"form","value":"{{ _.form_type }}","description":""}],"headers":[{"id":"pair_e25f9cacf80842ff8f8f32e512fdc0e2","name":"X-CSRF-TOKEN","value":"{{ _.token }}","description":""}],"authentication":{},"metaSortKey":-1680176735682,"isPrivate":false,"settingStoreCookies":true,"settingSendCookies":true,"settingDisableRenderRequestBody":false,"settingEncodeUrl":true,"settingRebuildPath":true,"settingFollowRedirects":"global","_type":"request"},{"_id":"req_bd0119d0ad6142199eb19143464c4430","parentId":"fld_bedf24f4d1d14619bd05616fc98f210c","modified":1680915315290,"created":1680177215894,"url":"{{ _.url }}/transactions","name":"getList","description":"","method":"GET","body":{},"parameters":[{"id":"pair_809f356df8ab409c9e66db44d34c055d","name":"form","value":"{{ _.form_type }}","description":""}],"headers":[{"id":"pair_37462f127fa34f89b14030095dfafcc1","name":"X-CSRF-TOKEN","value":"{{ _.token }}","description":""}],"authentication":{},"metaSortKey":-1680176734514,"isPrivate":false,"settingStoreCookies":true,"settingSendCookies":true,"settingDisableRenderRequestBody":false,"settingEncodeUrl":true,"settingRebuildPath":true,"settingFollowRedirects":"global","_type":"request"},{"_id":"req_d1234ac231c144d3a282e358364defb8","parentId":"fld_bedf24f4d1d14619bd05616fc98f210c","modified":1680915320677,"created":1680177215888,"url":"{{ _.url }}/transactions/{{ _.transaction_id }}","name":"update","description":"","method":"PUT","body":{"mimeType":"application/json","text":"{\n\t\"message\": \"Pagamento restante\"\n}\n"},"parameters":[{"id":"pair_c789013c283049fdadf3c2e1c2ac23ff","name":"form","value":"{{ _.form_type }}","description":""}],"headers":[{"name":"Content-Type","value":"application/json","id":"pair_776d0a73eb9a46018648aa6403a89ae4"},{"id":"pair_1c065c9cdeb5423aaf7f14ace0897ad2","name":"X-CSRF-TOKEN","value":"{{ _.token }}","description":""}],"authentication":{},"metaSortKey":-1680176722746,"isPrivate":false,"settingStoreCookies":true,"settingSendCookies":true,"settingDisableRenderRequestBody":false,"settingEncodeUrl":true,"settingRebuildPath":true,"settingFollowRedirects":"global","_type":"request"},{"_id":"req_399830d6cfb44221a5fec2c70f89d5dc","parentId":"fld_bedf24f4d1d14619bd05616fc98f210c","modified":1680915326094,"created":1680177215881,"url":"{{ _.url }}/transactions/{{ _.transaction_id }}","name":"delete","description":"","method":"DELETE","body":{},"parameters":[{"id":"pair_5c99821ca31146cba7189189507ab601","name":"form","value":"{{ _.form_type }}","description":""}],"headers":[{"id":"pair_875c7616f451468fac20f8e16eca3205","name":"X-CSRF-TOKEN","value":"{{ _.token }}","description":""}],"authentication":{},"metaSortKey":-1680176468757,"isPrivate":false,"settingStoreCookies":true,"settingSendCookies":true,"settingDisableRenderRequestBody":false,"settingEncodeUrl":true,"settingRebuildPath":true,"settingFollowRedirects":"global","_type":"request"},{"_id":"req_df5b323e19f84fa29e7aa475982979de","parentId":"fld_698e8fe0031e4a58acad3db4dc3cd7f7","modified":1680915332416,"created":1680177232428,"url":"{{ _.url }}/transaction_types","name":"store","description":"","method":"POST","body":{"mimeType":"application/json","text":"{\n\t\"type\": \"TED\"\n}\n"},"parameters":[{"id":"pair_b26d6eb05cb34ce5ad62ae632c60dee7","name":"form","value":"{{ _.form_type }}","description":""}],"headers":[{"name":"Content-Type","value":"application/json","id":"pair_2f52098bf96144a08feacf7cb897bf21"},{"id":"pair_5f1c4902332b4e7fb13714347853f327","name":"X-CSRF-TOKEN","value":"{{ _.token }}","description":""}],"authentication":{},"metaSortKey":-1680176736850,"isPrivate":false,"settingStoreCookies":true,"settingSendCookies":true,"settingDisableRenderRequestBody":false,"settingEncodeUrl":true,"settingRebuildPath":true,"settingFollowRedirects":"global","_type":"request"},{"_id":"fld_698e8fe0031e4a58acad3db4dc3cd7f7","parentId":"wrk_f8c8ced6f005427f8b580f349fff0f14","modified":1680177232424,"created":1680177232424,"name":"TransactionType","description":"","environment":{},"environmentPropertyOrder":null,"metaSortKey":-1679786706641.1875,"_type":"request_group"},{"_id":"req_58fd2ae894e24b609d49b6725ca0c687","parentId":"fld_698e8fe0031e4a58acad3db4dc3cd7f7","modified":1680915337544,"created":1680177232451,"url":"{{ _.url }}/transaction_types/{{ _.transaction_type_id }}","name":"get","description":"","method":"GET","body":{},"parameters":[{"id":"pair_9a6bab269a274387920c5c756bb682d7","name":"form","value":"{{ _.form_type }}","description":""}],"headers":[{"id":"pair_e25f9cacf80842ff8f8f32e512fdc0e2","name":"X-CSRF-TOKEN","value":"{{ _.token }}","description":""}],"authentication":{},"metaSortKey":-1680176735682,"isPrivate":false,"settingStoreCookies":true,"settingSendCookies":true,"settingDisableRenderRequestBody":false,"settingEncodeUrl":true,"settingRebuildPath":true,"settingFollowRedirects":"global","_type":"request"},{"_id":"req_a73d8cc9fe2240899f20e8c83d687fa5","parentId":"fld_698e8fe0031e4a58acad3db4dc3cd7f7","modified":1680915342923,"created":1680177232445,"url":"{{ _.url }}/transaction_types","name":"getList","description":"","method":"GET","body":{},"parameters":[{"id":"pair_be00a91f45074e0fbac8d92af80f7a0c","name":"form","value":"{{ _.form_type }}","description":""}],"headers":[{"id":"pair_37462f127fa34f89b14030095dfafcc1","name":"X-CSRF-TOKEN","value":"{{ _.token }}","description":""}],"authentication":{},"metaSortKey":-1680176734514,"isPrivate":false,"settingStoreCookies":true,"settingSendCookies":true,"settingDisableRenderRequestBody":false,"settingEncodeUrl":true,"settingRebuildPath":true,"settingFollowRedirects":"global","_type":"request"},{"_id":"req_2788247a383841d8b72e4ca61de682e0","parentId":"fld_698e8fe0031e4a58acad3db4dc3cd7f7","modified":1680915348218,"created":1680177232440,"url":"{{ _.url }}/transaction_types/{{ _.transaction_type_id }}","name":"update","description":"","method":"PUT","body":{"mimeType":"application/json","text":"{\n\t\"type\": \"TED\"\n}\n"},"parameters":[{"id":"pair_6d241afb8ba34b2d8aa94969b5ddbd56","name":"form","value":"{{ _.form_type }}","description":""}],"headers":[{"name":"Content-Type","value":"application/json","id":"pair_776d0a73eb9a46018648aa6403a89ae4"},{"id":"pair_1c065c9cdeb5423aaf7f14ace0897ad2","name":"X-CSRF-TOKEN","value":"{{ _.token }}","description":""}],"authentication":{},"metaSortKey":-1680176722746,"isPrivate":false,"settingStoreCookies":true,"settingSendCookies":true,"settingDisableRenderRequestBody":false,"settingEncodeUrl":true,"settingRebuildPath":true,"settingFollowRedirects":"global","_type":"request"},{"_id":"req_11d1ced0a13248d8851625884edb832c","parentId":"fld_698e8fe0031e4a58acad3db4dc3cd7f7","modified":1680915353305,"created":1680177232434,"url":"{{ _.url }}/transaction_types/{{ _.transaction_type_id }}","name":"delete","description":"","method":"DELETE","body":{},"parameters":[{"id":"pair_252a042ac4634b178743b31da360cb17","name":"form","value":"{{ _.form_type }}","description":""}],"headers":[{"id":"pair_875c7616f451468fac20f8e16eca3205","name":"X-CSRF-TOKEN","value":"{{ _.token }}","description":""}],"authentication":{},"metaSortKey":-1680176468757,"isPrivate":false,"settingStoreCookies":true,"settingSendCookies":true,"settingDisableRenderRequestBody":false,"settingEncodeUrl":true,"settingRebuildPath":true,"settingFollowRedirects":"global","_type":"request"},{"_id":"env_4551f2e419feb79ac2b45332dffa2874d2c0fac0","parentId":"wrk_f8c8ced6f005427f8b580f349fff0f14","modified":1680915104447,"created":1679853943681,"name":"Base Environment","data":{"url":"http://api-laravel.local","token":"DqJh0efVK9DWuQ0zsF3SW9i53FhZy2WhzQqyna8M","account_id":1,"customer_id":1,"transaction_id":1,"address_id":50,"account_type_id":1,"transaction_type_id":1,"form_type":"xml"},"dataPropertyOrder":{"&":["url","token","account_id","customer_id","transaction_id","address_id","account_type_id","transaction_type_id","form_type"]},"color":null,"isPrivate":false,"metaSortKey":1679853943681,"_type":"environment"},{"_id":"jar_4551f2e419feb79ac2b45332dffa2874d2c0fac0","parentId":"wrk_f8c8ced6f005427f8b580f349fff0f14","modified":1680915137397,"created":1679853943683,"name":"Default Jar","cookies":[{"key":"XSRF-TOKEN","value":"eyJpdiI6InRqaW5HTUNGRkVHb0JIcFN5MTBFTFE9PSIsInZhbHVlIjoiOFJ1UXo2ZkxlRytWUVNvTVJYck9yOHIwcU5xL2ZBdmhZSytNUURwRU16bDhIclRKY09qZUlQUkRrVEN3akhjcFIzRWNkdzRiMmNpUVd2TnFyTWxXS2JvVThqRmszdG1uUlRqQ3NpVU82blE0ZGJ3MEJNc0Z0d1Y4YWxOek5wRkYiLCJtYWMiOiJiY2ZmYzU4OGUyNjU1MjgxZmU2ZWJiOGUxMGYxZDFmYjdhNzkzMWIwYzI3OTRhNzQxNGY4YzJhZDJlZGFlMzJiIiwidGFnIjoiIn0%3D","expires":"2023-04-08T02:52:17.000Z","maxAge":7200,"domain":"api-laravel.local","path":"/","extensions":["samesite=lax"],"hostOnly":true,"creation":"2023-03-30T12:22:01.202Z","lastAccessed":"2023-04-08T00:52:17.397Z","id":"680553720049603"},{"key":"laravel_session","value":"eyJpdiI6IkRVcTVnUDM2ZkFqcnlNeUEzOWJ3UkE9PSIsInZhbHVlIjoiOHZWdVk0TmNJblJYaURXc1lVdUFKSGd0bFdYVWkxWncyNXhxTUk4bnNGRXFHcGpZTXAvZGNwSnZZd25sWms1alFTNHJxbFZBTytuaVVXRFdZcUg2c0lJZDNrWTREK010SWNvem5aVi9aeTlZODhnTW4vUG1nMWNLTmcvM3lBZVYiLCJtYWMiOiIyOWY2YzFhZGI3MTQ5ZmNjNjQ5NmI4ZWNkNjgzODBlNWUxOWMyZGM4NGI2N2UzNDVlMTE2NGU4ZDJjZGU4YTE5IiwidGFnIjoiIn0%3D","expires":"2023-04-08T02:52:17.000Z","maxAge":7200,"domain":"api-laravel.local","path":"/","httpOnly":true,"extensions":["samesite=lax"],"hostOnly":true,"creation":"2023-03-30T12:22:01.202Z","lastAccessed":"2023-04-08T00:52:17.397Z","id":"003258604802157894"}],"_type":"cookie_jar"},{"_id":"spc_fc3dc9dbc7874c408ae0d7387ec293ab","parentId":"wrk_f8c8ced6f005427f8b580f349fff0f14","modified":1679853943676,"created":1679853943676,"fileName":"API Laravel","contents":"","contentType":"yaml","_type":"api_spec"}]}